{
  "total_folds": 5,
  "completed_folds": 5,
  "fold_results": {
    "0": {
      "metrics": {
        "val_loss_X": 0.0006202540826052427,
        "val_loss_Y": 0.001235501142218709,
        "val_mae_X": 0.01870376244187355,
        "val_mae_Y": 0.02733512409031391,
        "val_r2_X": 0.974318265914917,
        "val_r2_Y": 0.9491117596626282,
        "val_mae": 0.023019444197416306,
        "val_dec1_cross_entropy": 0.670166552066803,
        "val_dec1_self_entropy": 0.456132173538208,
        "val_dec2_cross_entropy": -0.3585798144340515,
        "val_dec2_self_entropy": 0.4702949821949005,
        "val_notears": 0.0,
        "val_loss": 0.08950634300708771,
        "test_loss_X": 0.0006968739908188581,
        "test_loss_Y": 0.001307378988713026,
        "test_mae_X": 0.0197016391903162,
        "test_mae_Y": 0.028231896460056305,
        "test_r2_X": 0.9703682661056519,
        "test_r2_Y": 0.9439919590950012,
        "test_mae": 0.023966770619153976,
        "test_dec1_cross_entropy": 0.6697232127189636,
        "test_dec1_self_entropy": 0.4535638093948364,
        "test_dec2_cross_entropy": -0.34171921014785767,
        "test_dec2_self_entropy": 0.47166141867637634,
        "test_notears": 0.0,
        "test_loss": 0.09028930962085724,
        "trainable_params": 9644,
        "total_training_time": 2774.3023121356964,
        "avg_time_per_epoch": 13.802499065351723
      },
      "best_checkpoint_path": null,
      "fold_dir": "/cluster/home/josephj/Masterarbeit/causaliT_new/experiments/stage_mask_off/k_0"
    },
    "1": {
      "metrics": {
        "val_loss_X": 0.0008105129818432033,
        "val_loss_Y": 0.002684753853827715,
        "val_mae_X": 0.022966889664530754,
        "val_mae_Y": 0.042399097234010696,
        "val_r2_X": 0.9663339257240295,
        "val_r2_Y": 0.8851500749588013,
        "val_mae": 0.03268299624323845,
        "val_dec1_cross_entropy": -1.045994520187378,
        "val_dec1_self_entropy": 0.5269981622695923,
        "val_dec2_cross_entropy": -1.6163992881774902,
        "val_dec2_self_entropy": 0.37795472145080566,
        "val_notears": 0.0,
        "val_loss": 0.0038056785706430674,
        "test_loss_X": 0.0009320497047156096,
        "test_loss_Y": 0.0028207595460116863,
        "test_mae_X": 0.02444113977253437,
        "test_mae_Y": 0.04370070993900299,
        "test_r2_X": 0.9609413743019104,
        "test_r2_Y": 0.8784371614456177,
        "test_mae": 0.03407092019915581,
        "test_dec1_cross_entropy": -1.0595306158065796,
        "test_dec1_self_entropy": 0.5277301073074341,
        "test_dec2_cross_entropy": -1.5870832204818726,
        "test_dec2_self_entropy": 0.37749797105789185,
        "test_notears": 0.0,
        "test_loss": 0.00406261021271348,
        "trainable_params": 9644,
        "total_training_time": 2765.2803428173065,
        "avg_time_per_epoch": 13.757613645857246
      },
      "best_checkpoint_path": null,
      "fold_dir": "/cluster/home/josephj/Masterarbeit/causaliT_new/experiments/stage_mask_off/k_1"
    },
    "2": {
      "metrics": {
        "val_loss_X": 0.0009131013066507876,
        "val_loss_Y": 0.0018824976868927479,
        "val_mae_X": 0.02388264238834381,
        "val_mae_Y": 0.03512359783053398,
        "val_r2_X": 0.9607672691345215,
        "val_r2_Y": 0.9175518751144409,
        "val_mae": 0.029503116384148598,
        "val_dec1_cross_entropy": -0.7066808938980103,
        "val_dec1_self_entropy": 0.4038313031196594,
        "val_dec2_cross_entropy": 0.2678871750831604,
        "val_dec2_self_entropy": 0.3029194176197052,
        "val_notears": 0.0,
        "val_loss": 3.8622848987579346,
        "test_loss_X": 0.0008993153460323811,
        "test_loss_Y": 0.001894028508104384,
        "test_mae_X": 0.023947879672050476,
        "test_mae_Y": 0.03506110981106758,
        "test_r2_X": 0.9618170857429504,
        "test_r2_Y": 0.9186788201332092,
        "test_mae": 0.02950449287891388,
        "test_dec1_cross_entropy": -0.7276002764701843,
        "test_dec1_self_entropy": 0.40406334400177,
        "test_dec2_cross_entropy": 0.2647804617881775,
        "test_dec2_self_entropy": 0.302971214056015,
        "test_notears": 0.0,
        "test_loss": 3.785806894302368,
        "trainable_params": 9644,
        "total_training_time": 2774.3397455215454,
        "avg_time_per_epoch": 13.802685301102215
      },
      "best_checkpoint_path": null,
      "fold_dir": "/cluster/home/josephj/Masterarbeit/causaliT_new/experiments/stage_mask_off/k_2"
    },
    "3": {
      "metrics": {
        "val_loss_X": 0.0007647430757060647,
        "val_loss_Y": 0.0015680562937632203,
        "val_mae_X": 0.021540209650993347,
        "val_mae_Y": 0.03140901029109955,
        "val_r2_X": 0.9686875343322754,
        "val_r2_Y": 0.9344344139099121,
        "val_mae": 0.026474611833691597,
        "val_dec1_cross_entropy": -0.2956092357635498,
        "val_dec1_self_entropy": 0.5658689141273499,
        "val_dec2_cross_entropy": -0.4457627236843109,
        "val_dec2_self_entropy": 0.36912301182746887,
        "val_notears": 0.0,
        "val_loss": 0.00881595816463232,
        "test_loss_X": 0.000913592055439949,
        "test_loss_Y": 0.001646624063141644,
        "test_mae_X": 0.023066602647304535,
        "test_mae_Y": 0.03187418729066849,
        "test_r2_X": 0.9616669416427612,
        "test_r2_Y": 0.9301910400390625,
        "test_mae": 0.027470391243696213,
        "test_dec1_cross_entropy": -0.28901588916778564,
        "test_dec1_self_entropy": 0.5658097863197327,
        "test_dec2_cross_entropy": -0.4335950016975403,
        "test_dec2_self_entropy": 0.37963515520095825,
        "test_notears": 0.0,
        "test_loss": 0.009026696905493736,
        "trainable_params": 9644,
        "total_training_time": 2760.926679611206,
        "avg_time_per_epoch": 13.735953629906497
      },
      "best_checkpoint_path": null,
      "fold_dir": "/cluster/home/josephj/Masterarbeit/causaliT_new/experiments/stage_mask_off/k_3"
    },
    "4": {
      "metrics": {
        "val_loss_X": 0.0008228330407291651,
        "val_loss_Y": 0.0018767064902931452,
        "val_mae_X": 0.022890815511345863,
        "val_mae_Y": 0.03426995500922203,
        "val_r2_X": 0.9662973880767822,
        "val_r2_Y": 0.9218829274177551,
        "val_mae": 0.02858038991689682,
        "val_dec1_cross_entropy": -1.2951550483703613,
        "val_dec1_self_entropy": 0.47839829325675964,
        "val_dec2_cross_entropy": -0.3132146894931793,
        "val_dec2_self_entropy": 0.4907013773918152,
        "val_notears": 0.0,
        "val_loss": 93.83733367919922,
        "test_loss_X": 0.0008055220823734999,
        "test_loss_Y": 0.0017911846516653895,
        "test_mae_X": 0.02234761416912079,
        "test_mae_Y": 0.03347775712609291,
        "test_r2_X": 0.9657524228096008,
        "test_r2_Y": 0.9234808087348938,
        "test_mae": 0.0279126837849617,
        "test_dec1_cross_entropy": -1.336462140083313,
        "test_dec1_self_entropy": 0.47923415899276733,
        "test_dec2_cross_entropy": -0.35323983430862427,
        "test_dec2_self_entropy": 0.48769381642341614,
        "test_notears": 0.0,
        "test_loss": 95.96939849853516,
        "trainable_params": 9644,
        "total_training_time": 2769.1515164375305,
        "avg_time_per_epoch": 13.776873216107116
      },
      "best_checkpoint_path": null,
      "fold_dir": "/cluster/home/josephj/Masterarbeit/causaliT_new/experiments/stage_mask_off/k_4"
    }
  },
  "statistics": {
    "val_loss_X": {
      "mean": 0.0007862888975068927,
      "std": 9.595358250233228e-05,
      "min": 0.0006202540826052427,
      "max": 0.0009131013066507876
    },
    "val_loss_Y": {
      "mean": 0.0018495030933991074,
      "std": 0.00048076672053659695,
      "min": 0.001235501142218709,
      "max": 0.002684753853827715
    },
    "val_mae_X": {
      "mean": 0.021996863931417466,
      "std": 0.001808275990607185,
      "min": 0.01870376244187355,
      "max": 0.02388264238834381
    },
    "val_mae_Y": {
      "mean": 0.034107356891036035,
      "std": 0.004958958624369199,
      "min": 0.02733512409031391,
      "max": 0.042399097234010696
    },
    "val_r2_X": {
      "mean": 0.9672808766365051,
      "std": 0.004377089951020374,
      "min": 0.9607672691345215,
      "max": 0.974318265914917
    },
    "val_r2_Y": {
      "mean": 0.9216262102127075,
      "std": 0.021291688818835936,
      "min": 0.8851500749588013,
      "max": 0.9491117596626282
    },
    "val_mae": {
      "mean": 0.028052111715078355,
      "std": 0.00321390205639309,
      "min": 0.023019444197416306,
      "max": 0.03268299624323845
    },
    "val_dec1_cross_entropy": {
      "mean": -0.5346546292304992,
      "std": 0.6896606682088736,
      "min": -1.2951550483703613,
      "max": 0.670166552066803
    },
    "val_dec1_self_entropy": {
      "mean": 0.48624576926231383,
      "std": 0.056144738828655276,
      "min": 0.4038313031196594,
      "max": 0.5658689141273499
    },
    "val_dec2_cross_entropy": {
      "mean": -0.4932138681411743,
      "std": 0.6154019710110064,
      "min": -1.6163992881774902,
      "max": 0.2678871750831604
    },
    "val_dec2_self_entropy": {
      "mean": 0.4021987020969391,
      "std": 0.0692935424238274,
      "min": 0.3029194176197052,
      "max": 0.4907013773918152
    },
    "val_notears": {
      "mean": 0.0,
      "std": 0.0,
      "min": 0.0,
      "max": 0.0
    },
    "val_loss": {
      "mean": 19.560349311539902,
      "std": 37.1680890396668,
      "min": 0.0038056785706430674,
      "max": 93.83733367919922
    },
    "test_loss_X": {
      "mean": 0.0008494706358760596,
      "std": 8.790058660275715e-05,
      "min": 0.0006968739908188581,
      "max": 0.0009320497047156096
    },
    "test_loss_Y": {
      "mean": 0.001891995151527226,
      "std": 0.000504926374974129,
      "min": 0.001307378988713026,
      "max": 0.0028207595460116863
    },
    "test_mae_X": {
      "mean": 0.022700975090265273,
      "std": 0.0016635809237470556,
      "min": 0.0197016391903162,
      "max": 0.02444113977253437
    },
    "test_mae_Y": {
      "mean": 0.03446913212537765,
      "std": 0.005141831159003991,
      "min": 0.028231896460056305,
      "max": 0.04370070993900299
    },
    "test_r2_X": {
      "mean": 0.9641092181205749,
      "std": 0.003553297708316034,
      "min": 0.9609413743019104,
      "max": 0.9703682661056519
    },
    "test_r2_Y": {
      "mean": 0.9189559578895569,
      "std": 0.021978864270198635,
      "min": 0.8784371614456177,
      "max": 0.9439919590950012
    },
    "test_mae": {
      "mean": 0.028585051745176317,
      "std": 0.0032852151210912557,
      "min": 0.023966770619153976,
      "max": 0.03407092019915581
    },
    "test_dec1_cross_entropy": {
      "mean": -0.5485771417617797,
      "std": 0.7022126890843634,
      "min": -1.336462140083313,
      "max": 0.6697232127189636
    },
    "test_dec1_self_entropy": {
      "mean": 0.4860802412033081,
      "std": 0.05643132165157882,
      "min": 0.40406334400177,
      "max": 0.5658097863197327
    },
    "test_dec2_cross_entropy": {
      "mean": -0.49017136096954345,
      "std": 0.6028527267467155,
      "min": -1.5870832204818726,
      "max": 0.2647804617881775
    },
    "test_dec2_self_entropy": {
      "mean": 0.40389191508293154,
      "std": 0.06794922054374893,
      "min": 0.302971214056015,
      "max": 0.48769381642341614
    },
    "test_notears": {
      "mean": 0.0,
      "std": 0.0,
      "min": 0.0,
      "max": 0.0
    },
    "test_loss": {
      "mean": 19.971716801915317,
      "std": 38.02661876127707,
      "min": 0.00406261021271348,
      "max": 95.96939849853516
    },
    "trainable_params": {
      "mean": 9644.0,
      "std": 0.0,
      "min": 9644.0,
      "max": 9644.0
    },
    "total_training_time": {
      "mean": 2768.800119304657,
      "std": 5.205092576411775,
      "min": 2760.926679611206,
      "max": 2774.3397455215454
    },
    "avg_time_per_epoch": {
      "mean": 13.77512497166496,
      "std": 0.025895982967222873,
      "min": 13.735953629906497,
      "max": 13.802685301102215
    }
  },
  "best_fold": {
    "fold_number": 0,
    "val_mae": 0.023019444197416306,
    "metrics": {
      "val_loss_X": 0.0006202540826052427,
      "val_loss_Y": 0.001235501142218709,
      "val_mae_X": 0.01870376244187355,
      "val_mae_Y": 0.02733512409031391,
      "val_r2_X": 0.974318265914917,
      "val_r2_Y": 0.9491117596626282,
      "val_mae": 0.023019444197416306,
      "val_dec1_cross_entropy": 0.670166552066803,
      "val_dec1_self_entropy": 0.456132173538208,
      "val_dec2_cross_entropy": -0.3585798144340515,
      "val_dec2_self_entropy": 0.4702949821949005,
      "val_notears": 0.0,
      "val_loss": 0.08950634300708771,
      "test_loss_X": 0.0006968739908188581,
      "test_loss_Y": 0.001307378988713026,
      "test_mae_X": 0.0197016391903162,
      "test_mae_Y": 0.028231896460056305,
      "test_r2_X": 0.9703682661056519,
      "test_r2_Y": 0.9439919590950012,
      "test_mae": 0.023966770619153976,
      "test_dec1_cross_entropy": 0.6697232127189636,
      "test_dec1_self_entropy": 0.4535638093948364,
      "test_dec2_cross_entropy": -0.34171921014785767,
      "test_dec2_self_entropy": 0.47166141867637634,
      "test_notears": 0.0,
      "test_loss": 0.09028930962085724,
      "trainable_params": 9644,
      "total_training_time": 2774.3023121356964,
      "avg_time_per_epoch": 13.802499065351723
    },
    "checkpoint_path": null
  }
}